{
  "count": 354,
  "uniques": 103,
  "views": [
    {
      "timestamp": "2021-04-30T00:00:00Z",
      "count": 156,
      "uniques": 37
    },
    {
      "timestamp": "2021-05-01T00:00:00Z",
      "count": 9,
      "uniques": 9
    },
    {
      "timestamp": "2021-05-02T00:00:00Z",
      "count": 18,
      "uniques": 12
    },
    {
      "timestamp": "2021-05-03T00:00:00Z",
      "count": 43,
      "uniques": 10
    },
    {
      "timestamp": "2021-05-04T00:00:00Z",
      "count": 19,
      "uniques": 6
    },
    {
      "timestamp": "2021-05-05T00:00:00Z",
      "count": 26,
      "uniques": 8
    },
    {
      "timestamp": "2021-05-06T00:00:00Z",
      "count": 83,
      "uniques": 21
    }
  ]
}