{
  "count": 285,
  "uniques": 87,
  "views": [
    {
      "timestamp": "2021-11-01T00:00:00Z",
      "count": 37,
      "uniques": 16
    },
    {
      "timestamp": "2021-11-02T00:00:00Z",
      "count": 43,
      "uniques": 13
    },
    {
      "timestamp": "2021-11-03T00:00:00Z",
      "count": 35,
      "uniques": 13
    },
    {
      "timestamp": "2021-11-04T00:00:00Z",
      "count": 38,
      "uniques": 12
    },
    {
      "timestamp": "2021-11-05T00:00:00Z",
      "count": 55,
      "uniques": 12
    },
    {
      "timestamp": "2021-11-06T00:00:00Z",
      "count": 47,
      "uniques": 13
    },
    {
      "timestamp": "2021-11-07T00:00:00Z",
      "count": 30,
      "uniques": 8
    }
  ]
}