{
  "count": 337,
  "uniques": 46,
  "views": [
    {
      "timestamp": "2024-03-31T00:00:00Z",
      "count": 29,
      "uniques": 5
    },
    {
      "timestamp": "2024-04-01T00:00:00Z",
      "count": 31,
      "uniques": 6
    },
    {
      "timestamp": "2024-04-02T00:00:00Z",
      "count": 59,
      "uniques": 10
    },
    {
      "timestamp": "2024-04-03T00:00:00Z",
      "count": 71,
      "uniques": 9
    },
    {
      "timestamp": "2024-04-04T00:00:00Z",
      "count": 32,
      "uniques": 6
    },
    {
      "timestamp": "2024-04-05T00:00:00Z",
      "count": 44,
      "uniques": 5
    },
    {
      "timestamp": "2024-04-06T00:00:00Z",
      "count": 71,
      "uniques": 5
    }
  ]
}