{
  "count": 347,
  "uniques": 94,
  "views": [
    {
      "timestamp": "2021-03-24T00:00:00Z",
      "count": 39,
      "uniques": 13
    },
    {
      "timestamp": "2021-03-25T00:00:00Z",
      "count": 115,
      "uniques": 18
    },
    {
      "timestamp": "2021-03-26T00:00:00Z",
      "count": 72,
      "uniques": 24
    },
    {
      "timestamp": "2021-03-27T00:00:00Z",
      "count": 18,
      "uniques": 10
    },
    {
      "timestamp": "2021-03-28T00:00:00Z",
      "count": 14,
      "uniques": 6
    },
    {
      "timestamp": "2021-03-29T00:00:00Z",
      "count": 24,
      "uniques": 8
    },
    {
      "timestamp": "2021-03-30T00:00:00Z",
      "count": 65,
      "uniques": 15
    }
  ]
}