{
  "count": 217,
  "uniques": 63,
  "views": [
    {
      "timestamp": "2021-05-21T00:00:00Z",
      "count": 61,
      "uniques": 17
    },
    {
      "timestamp": "2021-05-22T00:00:00Z",
      "count": 14,
      "uniques": 5
    },
    {
      "timestamp": "2021-05-23T00:00:00Z",
      "count": 21,
      "uniques": 7
    },
    {
      "timestamp": "2021-05-24T00:00:00Z",
      "count": 20,
      "uniques": 4
    },
    {
      "timestamp": "2021-05-25T00:00:00Z",
      "count": 26,
      "uniques": 9
    },
    {
      "timestamp": "2021-05-26T00:00:00Z",
      "count": 29,
      "uniques": 9
    },
    {
      "timestamp": "2021-05-27T00:00:00Z",
      "count": 46,
      "uniques": 12
    }
  ]
}